django_cryptography/__init__.py
django_cryptography/conf.py
django_cryptography/fields.py
django_cryptography/core/__init__.py
django_cryptography/core/signing.py
django_cryptography/utils/__init__.py
django_cryptography/utils/crypto.py
django_cryptography/utils/version.py
tests/fields/__init__.py
tests/fields/models.py
tests/fields/test_encrypted.py
tests/fields/test_pickle.py
tests/fields/test_migrations_encrypted_default/0001_initial.py
tests/fields/test_migrations_encrypted_default/0002_integerencryptedmodel_field_2.py
tests/fields/test_migrations_encrypted_default/__init__.py
tests/fields/test_migrations_normal_to_encrypted/0001_initial.py
tests/fields/test_migrations_normal_to_encrypted/0002_rename_fields.py
tests/fields/test_migrations_normal_to_encrypted/0003_add_encrypted_fields.py
tests/fields/test_migrations_normal_to_encrypted/0004_migrate_data.py
tests/fields/test_migrations_normal_to_encrypted/0005_remove_old_fields.py
tests/fields/test_migrations_normal_to_encrypted/__init__.py
tests/signing/__init__.py
tests/signing/tests.py
tests/utils/__init__.py
tests/utils/crypto/__init__.py
tests/utils/crypto/tests.py
tests/version/__init__.py
tests/version/tests.py
django_cryptography-1.0.dist-info/LICENSE
django_cryptography-1.0.dist-info/METADATA
django_cryptography-1.0.dist-info/WHEEL
django_cryptography-1.0.dist-info/top_level.txt
django_cryptography-1.0.dist-info/RECORD
